macos_keychain/__init__.py
macos_keychain/main.py
macos_keychain-0.2.1.dist-info/LICENSE
macos_keychain-0.2.1.dist-info/WHEEL
macos_keychain-0.2.1.dist-info/METADATA
macos_keychain-0.2.1.dist-info/RECORD
